transcoders_slim/__init__.py
transcoders_slim/load_pretrained.py
transcoders_slim/transcoder.py
transcoders_slim/sae_training/__init__.py
transcoders_slim/sae_training/config.py
transcoders_slim/sae_training/sparse_autoencoder.py
transcoders_slim-0.2.1.dist-info/METADATA
transcoders_slim-0.2.1.dist-info/WHEEL
transcoders_slim-0.2.1.dist-info/RECORD
