Metadata-Version: 2.3
Name: transcoders-slim
Version: 0.2.1
Summary: A template for python projects in PDM
Author-email: Daniel Tan <dtch1997@users.noreply.github.com>, Daniel CH Tan <dtch1997@users.noreply.github.com>
License: MIT
Requires-Python: >=3.10
Requires-Dist: einops>=0.6.0
Requires-Dist: huggingface-hub>=0.23.0
Requires-Dist: jaxtyping>=0.2.28
Requires-Dist: torch>=2.3.0
Requires-Dist: transformer-lens>=1.14.0
Provides-Extra: test
Requires-Dist: pre-commit>=3.7.0; extra == 'test'
Requires-Dist: pyright>=1.1.361; extra == 'test'
Requires-Dist: pytest>=8.2.0; extra == 'test'
Requires-Dist: ruff>=0.4.3; extra == 'test'
